{
  "name": {
    "en": "Wattsonic Inverter",
    "de": "Wattsonic Wechselrichter"
  },
  "class": "solarpanel",
  "energy": {
    "batteries": [
      "OTHER"
    ]
  },
  "capabilities": [
    "measure_power",
    "measure_power.pv1input",
    "measure_power.pv2input",
    "measure_current.phase1",
    "measure_current.phase2",
    "measure_current.phase3",
    "measure_temperature.invertor",
    "meter_power",
    "meter_power.daily"
  ],
  "capabilitiesOptions": {
    "measure_power": {
      "decimals": 0,
      "title": {
        "en": "Solar Power",
        "de": "Solarleistung"
      }
    },
    "measure_power.pv1input": {
      "decimals": 0,
      "title": {
        "en": "PV1 input",
        "de": "PV-Strang 1 Eingang"
      }
    },
    "measure_power.pv2input": {
      "decimals": 0,
      "title": {
        "en": "PV2 input",
        "de": "PV-Strang 2 Eingang"
      }
    },
    "measure_current.phase1": {
      "title": {
        "en": "AC Current phase1",
        "de": "AC-Strom Phase 1"
      }
    },
    "measure_current.phase2": {
      "title": {
        "en": "AC Current phase2",
        "de": "AC-Strom Phase 2"
      }
    },
    "measure_current.phase3": {
      "title": {
        "en": "AC Current phase3",
        "de": "AC-Strom Phase 3"
      }
    },
    "measure_temperature.invertor": {
      "title": {
        "en": "Heatsink temperature",
        "nl": "Heatsink temperatuur",
        "de": "Kühlkörpertemperatur"
      },
      "decimals": 2
    },
    "meter_power": {
      "title": {
        "en": "Total Yield",
        "nl": "Totale opbrengst",
        "de": "Gesamtertrag"
      },
      "decimals": 1
    },
    "meter_power.daily": {
      "title": {
        "en": "Total Day Yield",
        "nl": "Totale dag opbrengst",
        "de": "Tagesgesamtertrag"
      },
      "decimals": 1,
      "icon": "/assets/total_yield.svg"
    }
  },
  "platforms": [
    "local"
  ],
  "connectivity": [
    "lan"
  ],
  "images": {
    "small": "{{driverAssetsPath}}/images/small.png",
    "large": "{{driverAssetsPath}}/images/large.png"
  },
  "pair": [
    {
      "id": "start"
    }
  ],
  "settings": [
    {
      "type": "group",
      "label": {
        "en": "Inverter settings",
        "de": "Wechselrichtereinstellungen"
      },
      "children": [
        {
          "id": "address",
          "type": "text",
          "value": "0.0.0.0",
          "label": {
            "en": "IP Address",
            "de": "IP-Adresse"
          }
        },
        {
          "id": "port",
          "type": "number",
          "value": 1502,
          "step": 1,
          "label": {
            "en": "Port",
            "de": "Port"
          }
        },
        {
          "id": "id",
          "type": "number",
          "value": 1,
          "step": 1,
          "attr": {
            "min": 0,
            "max": 260
          },
          "label": {
            "en": "Inverter ID",
            "nl": "Inverter ID",
            "de": "Wechselrichter-ID"
          }
        }
      ]
    }
  ]
}