{
    "title": {
        "en": "Active Power Limit",
        "de": "Aktive Leistungsbeschränkung"
    },
    "args": [
        {
            "type": "range",
            "name": "value",
            "title": {
                "en": "percentage",
                "de": "Prozent"
            },
            "min": 0,
            "max": 100,
            "step": 1,
            "labelDecimals": 0
        },
        {
            "type": "device",
            "name": "device",
            "filter": "driver_id=invertor|invertorwithbatt"
        }
    ]
}